VSGenerator/DVSNet.py
VSGenerator/__init__.py
VSGenerator/_BgoVAE/__init__.py
VSGenerator/_BgoVAE/svae.py
VSGenerator/_VSGNN/__init__.py
VSGenerator/_VSGNN/vsg.py
VSGenerator-0.1.0.dist-info/METADATA
VSGenerator-0.1.0.dist-info/WHEEL
VSGenerator-0.1.0.dist-info/top_level.txt
VSGenerator-0.1.0.dist-info/RECORD
