Metadata-Version: 2.1
Name: VSGenerator
Version: 0.1.0
Summary: Dynamic Virtual Space generation neural Network.
Home-page: https://github.com/Bin-Cao/Bgolearn
Author: CaoBin
Author-email: binjacobcao@gmail.com
Maintainer: CaoBin
Maintainer-email: binjacobcao@gmail.com
License: MIT License
Classifier: Development Status :: 3 - Alpha
Classifier: Intended Audience :: Developers
Classifier: Topic :: Software Development :: Build Tools
Classifier: License :: OSI Approved :: MIT License
Classifier: Programming Language :: Python :: 3
Requires-Python: >=3.5
Requires-Dist: tensorflow
Requires-Dist: pandas
Requires-Dist: numpy
